anonym/__init__.py
anonym/anonym.py
anonym/examples.py
anonym-0.1.1.dist-info/LICENSE
anonym-0.1.1.dist-info/METADATA
anonym-0.1.1.dist-info/WHEEL
anonym-0.1.1.dist-info/top_level.txt
anonym-0.1.1.dist-info/RECORD
