Metadata-Version: 2.1
Name: anonym
Version: 0.1.1
Summary: Python package anonym
Home-page: https://gitlab.com/datainnovatielab/public/anonym
Download-URL: https://gitlab.com/datainnovatielab/public/anonym/archive/0.1.1.tar.gz
Author: Erdogan Taskesen
Author-email: erdogan.taskesen@minienw.nl
Classifier: Programming Language :: Python :: 3
Classifier: License :: OSI Approved :: MIT License
Classifier: Operating System :: OS Independent
Requires-Python: >=3
License-File: LICENSE
Requires-Dist: Faker
Requires-Dist: datazets
Requires-Dist: numpy
Requires-Dist: spacy
Requires-Dist: ismember
Requires-Dist: pandas
